{"timesteps": {"10": {"duration": 0.9528594017028809}, "20": {"duration": 0.9471516609191895}, "30": {"duration": 1.0036170482635498}, "40": {"duration": 1.0636143684387207}, "50": {"duration": 1.0538010597229004}, "60": {"duration": 1.2667183876037598}, "70": {"duration": 1.0518178939819336}, "80": {"duration": 1.0457382202148438}, "90": {"duration": 1.0458247661590576}, "100": {"duration": 1.0135009288787842}, "110": {"duration": 1.0541701316833496}, "120": {"duration": 1.0364124774932861}, "130": {"duration": 1.057987928390503}, "140": {"duration": 1.0375440120697021}, "150": {"duration": 1.0377988815307617}, "160": {"duration": 1.042820692062378}, "170": {"duration": 1.0262174606323242}, "180": {"duration": 1.0488684177398682}, "190": {"duration": 1.0618231296539307}}, "metadata": {"sla": 29.198052945559354, "base_allocations": {"crop": {"yolov5n": 1, "yolov5s": 1, "yolov5m": 2, "yolov5l": 4, "yolov5x": 8, "yolov5xs": 8, "yolov5xss": 8}, "classification": {"resnet18": 1, "resnet34": 2, "resnet50": 4, "resnet101": 8, "resnet152": 8, "resnet152s": 8, "resnet152ss": 8}, "crops": {"yolov5n": 1, "yolov5s": 1, "yolov5m": 2, "yolov5l": 4, "yolov5x": 8, "yolov5xs": 8, "yolov5xss": 8}, "cropss": {"yolov5n": 1, "yolov5s": 1, "yolov5m": 2, "yolov5l": 4, "yolov5x": 8, "yolov5xs": 8, "yolov5xss": 8}, "cropsss": {"yolov5n": 1, "yolov5s": 1, "yolov5m": 2, "yolov5l": 4, "yolov5x": 8, "yolov5xs": 8, "yolov5xss": 8}, "cropssss": {"yolov5n": 1, "yolov5s": 1, "yolov5m": 2, "yolov5l": 4, "yolov5x": 8, "yolov5xs": 8, "yolov5xss": 8}, "cropsssss": {"yolov5n": 1, "yolov5s": 1, "yolov5m": 2, "yolov5l": 4, "yolov5x": 8, "yolov5xs": 8, "yolov5xss": 8}, "cropssssss": {"yolov5n": 1, "yolov5s": 1, "yolov5m": 2, "yolov5l": 4, "yolov5x": 8, "yolov5xs": 8, "yolov5xss": 8}}, "stage_wise_slas": {"crop": 3.9053146438189907, "classification": 1.8608504388264246, "crops": 3.9053146438189907, "cropss": 3.9053146438189907, "cropsss": 3.9053146438189907, "cropssss": 3.9053146438189907, "cropsssss": 3.9053146438189907, "cropssssss": 3.9053146438189907}}}